somethingstupid/__init__.py
something_stupid-0.0.3.dist-info/METADATA
something_stupid-0.0.3.dist-info/WHEEL
something_stupid-0.0.3.dist-info/RECORD
