Metadata-Version: 2.1
Name: something-stupid
Version: 0.0.3
Summary: 
Author: ivenpoker
Author-email: ivenpoker@gmail.com
Requires-Python: >=3.11,<4.0
Classifier: Programming Language :: Python :: 3
Classifier: Programming Language :: Python :: 3.11
Requires-Dist: poetry (>=1.5.1,<2.0.0)
